merlinpyspark/__init__.py
merlinpyspark/__main__.py
merlinpyspark/config.py
merlinpyspark/model.py
merlinpyspark/sink.py
merlinpyspark/source.py
merlinpyspark/version.py
merlinpyspark/spec/__init__.py
merlinpyspark/spec/prediction_job_pb2.py
merlinpyspark/spec/prediction_job_pb2.pyi
merlin_batch_predictor-0.49.4.dist-info/METADATA
merlin_batch_predictor-0.49.4.dist-info/WHEEL
merlin_batch_predictor-0.49.4.dist-info/entry_points.txt
merlin_batch_predictor-0.49.4.dist-info/top_level.txt
merlin_batch_predictor-0.49.4.dist-info/RECORD
