Metadata-Version: 2.1
Name: merlin-batch-predictor
Version: 0.49.4
Summary: Base PySpark application for running Merlin prediction batch job
Author-email: merlin-dev@gojek.com
Requires-Python: >=3.9,<3.11
Requires-Dist: cloudpickle==2.0.0
Requires-Dist: findspark==2.0.1
Requires-Dist: merlin-sdk==0.49.4
Requires-Dist: mlflow==1.26.1
Requires-Dist: pyarrow<=17.0.0,>=0.14.1
Requires-Dist: pyspark==3.1.3
Requires-Dist: setuptools<75
Provides-Extra: test
Requires-Dist: pytest; extra == "test"
Requires-Dist: pytest-cov; extra == "test"
Requires-Dist: mypy; extra == "test"
Requires-Dist: google-cloud-bigquery; extra == "test"
Requires-Dist: scikit-learn>=1.1.2; extra == "test"
Requires-Dist: joblib<1.2.0,>=0.13.0; extra == "test"
Requires-Dist: mypy-protobuf>=1.19; extra == "test"
Requires-Dist: types-PyYAML; extra == "test"
